[ {
  "invoked" : 1044018306,
  "entryPoint" : "hProjekt.model.grid.Statue#spawnAmulet()",
  "arguments" : [ ],
  "calls" : [ {
    "id" : 1044018306,
    "methodCalls" : [ {
      "methodName" : "getPosition",
      "invocations" : [ {
        "return" : 1296043639,
        "parameter" : [ ]
      } ]
    }, {
      "methodName" : "getHexGrid",
      "invocations" : [ {
        "return" : 540278073,
        "parameter" : [ ]
      } ]
    } ]
  }, {
    "id" : 540278073,
    "methodCalls" : [ {
      "methodName" : "getTileAt",
      "invocations" : [ {
        "return" : 0,
        "parameter" : [ 1922251979 ]
      }, {
        "return" : 1112743451,
        "parameter" : [ 1046302571 ]
      } ]
    } ]
  } ],
  "objects" : [ {
    "type" : "hProjekt.model.grid.Statue",
    "fields" : [ {
      "name" : "type",
      "type" : "hProjekt.model.grid.Structure$Type",
      "value" : "STATUE",
      "id" : 972811892
    }, {
      "name" : "hexGrid",
      "type" : "hProjekt.testOverrides.TestHexGridImpl",
      "fields" : [ {
        "name" : "biggestAreas",
        "type" : "java.util.Map",
        "value" : [ [ {
          "type" : "hProjekt.model.grid.Tile$Type",
          "value" : "PLAINS",
          "id" : 153245266
        }, {
          "type" : "java.util.Set",
          "value" : [ {
            "type" : "hProjekt.model.grid.TilePosition",
            "fields" : [ {
              "name" : "r",
              "type" : "java.lang.Integer",
              "value" : "0",
              "id" : 1899433964
            }, {
              "name" : "q",
              "id" : 1899433964
            } ],
            "id" : 1296043639
          }, {
            "type" : "hProjekt.model.grid.TilePosition",
            "fields" : [ {
              "name" : "r",
              "type" : "java.lang.Integer",
              "value" : "1",
              "id" : 659763564
            }, {
              "name" : "q",
              "id" : 1899433964
            } ],
            "id" : 344610846
          }, {
            "type" : "hProjekt.model.grid.TilePosition",
            "fields" : [ {
              "name" : "r",
              "id" : 1899433964
            }, {
              "name" : "q",
              "id" : 659763564
            } ],
            "id" : 1509220174
          }, {
            "type" : "hProjekt.model.grid.TilePosition",
            "fields" : [ {
              "name" : "r",
              "type" : "java.lang.Integer",
              "value" : "-1",
              "id" : 826945968
            }, {
              "name" : "q",
              "id" : 659763564
            } ],
            "id" : 1712405372
          }, {
            "type" : "hProjekt.model.grid.TilePosition",
            "fields" : [ {
              "name" : "r",
              "id" : 826945968
            }, {
              "name" : "q",
              "id" : 1899433964
            } ],
            "id" : 1919277981
          }, {
            "type" : "hProjekt.model.grid.TilePosition",
            "fields" : [ {
              "name" : "r",
              "id" : 1899433964
            }, {
              "name" : "q",
              "id" : 826945968
            } ],
            "id" : 879306599
          }, {
            "type" : "hProjekt.model.grid.TilePosition",
            "fields" : [ {
              "name" : "r",
              "id" : 659763564
            }, {
              "name" : "q",
              "id" : 826945968
            } ],
            "id" : 1268289547
          } ],
          "id" : 1265341013
        } ] ],
        "id" : 1241036157
      }, {
        "name" : "random",
        "type" : "java.util.Random",
        "fields" : [ {
          "name" : "haveNextNextGaussian",
          "type" : "java.lang.Boolean",
          "value" : "false",
          "id" : 1728554175
        }, {
          "name" : "nextNextGaussian",
          "type" : "java.lang.Double",
          "value" : "0.0",
          "id" : 196064189
        }, {
          "name" : "seed",
          "type" : "java.util.concurrent.atomic.AtomicLong",
          "fields" : [ {
            "name" : "value",
            "type" : "java.lang.Long",
            "value" : "32618091863046",
            "id" : 1525064256
          } ],
          "id" : 290986000
        } ],
        "id" : 1260479657
      }, {
        "name" : "structures",
        "type" : "java.util.Map",
        "value" : [ [ {
          "id" : 1296043639
        }, {
          "id" : 1044018306
        } ] ],
        "id" : 1455007548
      }, {
        "name" : "tiles",
        "type" : "java.util.Map",
        "value" : [ [ {
          "id" : 1268289547
        }, {
          "type" : "hProjekt.model.grid.TileImpl",
          "fields" : [ {
            "name" : "area",
            "id" : 1265341013
          }, {
            "name" : "hasAmulet",
            "id" : 1728554175
          }, {
            "name" : "hexGrid",
            "id" : 540278073
          }, {
            "name" : "type",
            "id" : 153245266
          }, {
            "name" : "position",
            "id" : 1268289547
          } ],
          "id" : 2027427558
        } ], [ {
          "id" : 344610846
        }, {
          "type" : "hProjekt.model.grid.TileImpl",
          "fields" : [ {
            "name" : "area",
            "id" : 1265341013
          }, {
            "name" : "hasAmulet",
            "id" : 1728554175
          }, {
            "name" : "hexGrid",
            "id" : 540278073
          }, {
            "name" : "type",
            "id" : 153245266
          }, {
            "name" : "position",
            "id" : 344610846
          } ],
          "id" : 2055495569
        } ], [ {
          "id" : 1296043639
        }, {
          "type" : "hProjekt.model.grid.TileImpl",
          "fields" : [ {
            "name" : "area",
            "id" : 1265341013
          }, {
            "name" : "hasAmulet",
            "id" : 1728554175
          }, {
            "name" : "hexGrid",
            "id" : 540278073
          }, {
            "name" : "type",
            "id" : 153245266
          }, {
            "name" : "position",
            "id" : 1296043639
          } ],
          "id" : 524383279
        } ], [ {
          "id" : 1919277981
        }, {
          "type" : "hProjekt.model.grid.TileImpl",
          "fields" : [ {
            "name" : "area",
            "id" : 1265341013
          }, {
            "name" : "hasAmulet",
            "id" : 1728554175
          }, {
            "name" : "hexGrid",
            "id" : 540278073
          }, {
            "name" : "type",
            "id" : 153245266
          }, {
            "name" : "position",
            "id" : 1919277981
          } ],
          "id" : 616401119
        } ], [ {
          "id" : 1509220174
        }, {
          "type" : "hProjekt.model.grid.TileImpl",
          "fields" : [ {
            "name" : "area",
            "id" : 1265341013
          }, {
            "name" : "hasAmulet",
            "id" : 1728554175
          }, {
            "name" : "hexGrid",
            "id" : 540278073
          }, {
            "name" : "type",
            "id" : 153245266
          }, {
            "name" : "position",
            "id" : 1509220174
          } ],
          "id" : 182490344
        } ], [ {
          "id" : 1712405372
        }, {
          "type" : "hProjekt.model.grid.TileImpl",
          "fields" : [ {
            "name" : "area",
            "id" : 1265341013
          }, {
            "name" : "hasAmulet",
            "id" : 1728554175
          }, {
            "name" : "hexGrid",
            "id" : 540278073
          }, {
            "name" : "type",
            "id" : 153245266
          }, {
            "name" : "position",
            "id" : 1712405372
          } ],
          "id" : 1112743451
        } ], [ {
          "id" : 879306599
        }, {
          "type" : "hProjekt.model.grid.TileImpl",
          "fields" : [ {
            "name" : "area",
            "id" : 1265341013
          }, {
            "name" : "hasAmulet",
            "id" : 1728554175
          }, {
            "name" : "hexGrid",
            "id" : 540278073
          }, {
            "name" : "type",
            "id" : 153245266
          }, {
            "name" : "position",
            "id" : 879306599
          } ],
          "id" : 91706501
        } ] ],
        "id" : 1096248964
      } ],
      "id" : 540278073
    }, {
      "name" : "tilePosition",
      "id" : 1296043639
    }, {
      "name" : "direction",
      "type" : "hProjekt.model.grid.TilePosition$EdgeDirection",
      "value" : "NORTH_EAST",
      "id" : 2062253014
    } ],
    "id" : 1044018306
  }, {
    "type" : "hProjekt.model.grid.TilePosition",
    "fields" : [ {
      "name" : "r",
      "type" : "java.lang.Integer",
      "value" : "-2",
      "id" : 1976503781
    }, {
      "name" : "q",
      "type" : "java.lang.Integer",
      "value" : "2",
      "id" : 373703332
    } ],
    "id" : 1922251979
  }, {
    "type" : "hProjekt.model.grid.TilePosition",
    "fields" : [ {
      "name" : "r",
      "id" : 826945968
    }, {
      "name" : "q",
      "id" : 659763564
    } ],
    "id" : 1046302571
  }, {
    "type" : "null",
    "id" : 0
  } ],
  "expected" : {
    "type" : "hProjekt.model.grid.Statue",
    "fields" : [ {
      "name" : "type",
      "type" : "hProjekt.model.grid.Structure$Type",
      "value" : "STATUE",
      "id" : 972811892
    }, {
      "name" : "hexGrid",
      "type" : "hProjekt.testOverrides.TestHexGridImpl",
      "fields" : [ {
        "name" : "biggestAreas",
        "type" : "java.util.Map",
        "value" : [ [ {
          "type" : "hProjekt.model.grid.Tile$Type",
          "value" : "PLAINS",
          "id" : 153245266
        }, {
          "type" : "java.util.Set",
          "value" : [ {
            "type" : "hProjekt.model.grid.TilePosition",
            "fields" : [ {
              "name" : "r",
              "type" : "java.lang.Integer",
              "value" : "0",
              "id" : 1899433964
            }, {
              "name" : "q",
              "id" : 1899433964
            } ],
            "id" : 1296043639
          }, {
            "type" : "hProjekt.model.grid.TilePosition",
            "fields" : [ {
              "name" : "r",
              "type" : "java.lang.Integer",
              "value" : "1",
              "id" : 659763564
            }, {
              "name" : "q",
              "id" : 1899433964
            } ],
            "id" : 344610846
          }, {
            "type" : "hProjekt.model.grid.TilePosition",
            "fields" : [ {
              "name" : "r",
              "id" : 1899433964
            }, {
              "name" : "q",
              "id" : 659763564
            } ],
            "id" : 1509220174
          }, {
            "type" : "hProjekt.model.grid.TilePosition",
            "fields" : [ {
              "name" : "r",
              "type" : "java.lang.Integer",
              "value" : "-1",
              "id" : 826945968
            }, {
              "name" : "q",
              "id" : 659763564
            } ],
            "id" : 1712405372
          }, {
            "type" : "hProjekt.model.grid.TilePosition",
            "fields" : [ {
              "name" : "r",
              "id" : 826945968
            }, {
              "name" : "q",
              "id" : 1899433964
            } ],
            "id" : 1919277981
          }, {
            "type" : "hProjekt.model.grid.TilePosition",
            "fields" : [ {
              "name" : "r",
              "id" : 1899433964
            }, {
              "name" : "q",
              "id" : 826945968
            } ],
            "id" : 879306599
          }, {
            "type" : "hProjekt.model.grid.TilePosition",
            "fields" : [ {
              "name" : "r",
              "id" : 659763564
            }, {
              "name" : "q",
              "id" : 826945968
            } ],
            "id" : 1268289547
          } ],
          "id" : 1265341013
        } ] ],
        "id" : 1241036157
      }, {
        "name" : "random",
        "type" : "java.util.Random",
        "fields" : [ {
          "name" : "haveNextNextGaussian",
          "type" : "java.lang.Boolean",
          "value" : "false",
          "id" : 1728554175
        }, {
          "name" : "nextNextGaussian",
          "type" : "java.lang.Double",
          "value" : "0.0",
          "id" : 932384584
        }, {
          "name" : "seed",
          "type" : "java.util.concurrent.atomic.AtomicLong",
          "fields" : [ {
            "name" : "value",
            "type" : "java.lang.Long",
            "value" : "32618091863046",
            "id" : 1476939608
          } ],
          "id" : 290986000
        } ],
        "id" : 1260479657
      }, {
        "name" : "structures",
        "type" : "java.util.Map",
        "value" : [ [ {
          "id" : 1296043639
        }, {
          "id" : 1044018306
        } ] ],
        "id" : 1455007548
      }, {
        "name" : "tiles",
        "type" : "java.util.Map",
        "value" : [ [ {
          "id" : 1268289547
        }, {
          "type" : "hProjekt.model.grid.TileImpl",
          "fields" : [ {
            "name" : "area",
            "id" : 1265341013
          }, {
            "name" : "hasAmulet",
            "id" : 1728554175
          }, {
            "name" : "hexGrid",
            "id" : 540278073
          }, {
            "name" : "type",
            "id" : 153245266
          }, {
            "name" : "position",
            "id" : 1268289547
          } ],
          "id" : 2027427558
        } ], [ {
          "id" : 344610846
        }, {
          "type" : "hProjekt.model.grid.TileImpl",
          "fields" : [ {
            "name" : "area",
            "id" : 1265341013
          }, {
            "name" : "hasAmulet",
            "id" : 1728554175
          }, {
            "name" : "hexGrid",
            "id" : 540278073
          }, {
            "name" : "type",
            "id" : 153245266
          }, {
            "name" : "position",
            "id" : 344610846
          } ],
          "id" : 2055495569
        } ], [ {
          "id" : 1296043639
        }, {
          "type" : "hProjekt.model.grid.TileImpl",
          "fields" : [ {
            "name" : "area",
            "id" : 1265341013
          }, {
            "name" : "hasAmulet",
            "id" : 1728554175
          }, {
            "name" : "hexGrid",
            "id" : 540278073
          }, {
            "name" : "type",
            "id" : 153245266
          }, {
            "name" : "position",
            "id" : 1296043639
          } ],
          "id" : 524383279
        } ], [ {
          "id" : 1919277981
        }, {
          "type" : "hProjekt.model.grid.TileImpl",
          "fields" : [ {
            "name" : "area",
            "id" : 1265341013
          }, {
            "name" : "hasAmulet",
            "id" : 1728554175
          }, {
            "name" : "hexGrid",
            "id" : 540278073
          }, {
            "name" : "type",
            "id" : 153245266
          }, {
            "name" : "position",
            "id" : 1919277981
          } ],
          "id" : 616401119
        } ], [ {
          "id" : 1509220174
        }, {
          "type" : "hProjekt.model.grid.TileImpl",
          "fields" : [ {
            "name" : "area",
            "id" : 1265341013
          }, {
            "name" : "hasAmulet",
            "id" : 1728554175
          }, {
            "name" : "hexGrid",
            "id" : 540278073
          }, {
            "name" : "type",
            "id" : 153245266
          }, {
            "name" : "position",
            "id" : 1509220174
          } ],
          "id" : 182490344
        } ], [ {
          "id" : 1712405372
        }, {
          "type" : "hProjekt.model.grid.TileImpl",
          "fields" : [ {
            "name" : "area",
            "id" : 1265341013
          }, {
            "name" : "hasAmulet",
            "type" : "java.lang.Boolean",
            "value" : "true",
            "id" : 1182888954
          }, {
            "name" : "hexGrid",
            "id" : 540278073
          }, {
            "name" : "type",
            "id" : 153245266
          }, {
            "name" : "position",
            "id" : 1712405372
          } ],
          "id" : 1112743451
        } ], [ {
          "id" : 879306599
        }, {
          "type" : "hProjekt.model.grid.TileImpl",
          "fields" : [ {
            "name" : "area",
            "id" : 1265341013
          }, {
            "name" : "hasAmulet",
            "id" : 1728554175
          }, {
            "name" : "hexGrid",
            "id" : 540278073
          }, {
            "name" : "type",
            "id" : 153245266
          }, {
            "name" : "position",
            "id" : 879306599
          } ],
          "id" : 91706501
        } ] ],
        "id" : 1096248964
      } ],
      "id" : 540278073
    }, {
      "name" : "tilePosition",
      "id" : 1296043639
    }, {
      "name" : "direction",
      "type" : "hProjekt.model.grid.TilePosition$EdgeDirection",
      "value" : "NORTH_EAST",
      "id" : 2062253014
    } ],
    "id" : 1044018306
  }
} ]